tkpy/__attrs__.py
tkpy/__init__.py
tkpy/buildings.py
tkpy/exception.py
tkpy/farmlist.py
tkpy/login.py
tkpy/map.py
tkpy/notepads.py
tkpy/rally_point.py
tkpy/villages.py
tkpy/enums/__init__.py
tkpy/enums/building.py
tkpy/enums/tribe.py
tkpy/enums/troop.py
tkpy/models/__init__.py
tkpy/models/config.py
tkpy/models/connection.py
tkpy/models/credential.py
tkpy/models/schema.sql
tkpy-0.0.1b4.dist-info/LICENSE
tkpy-0.0.1b4.dist-info/METADATA
tkpy-0.0.1b4.dist-info/WHEEL
tkpy-0.0.1b4.dist-info/top_level.txt
tkpy-0.0.1b4.dist-info/RECORD
