Metadata-Version: 2.1
Name: tkpy
Version: 0.0.1b4
Summary: Travian: Kingdom utilities for your need.
Home-page: https://github.com/didadadida93/tkpy
Author: didadadida93
Author-email: didadadida93@gmail.com
License: MIT
Platform: UNKNOWN
Classifier: Development Status :: 4 - Beta
Classifier: Programming Language :: Python :: 3.6
Classifier: Programming Language :: Python :: 3.7
Classifier: Programming Language :: Python :: 3.8
Classifier: License :: OSI Approved :: MIT License
Classifier: Intended Audience :: Developers
Classifier: Topic :: Utilities
Requires-Dist: requests
